MANIFEST.in
README.txt
setup.py
navigation/__init__.py
navigation/admin.py
navigation/context_processors.py
navigation/fields.py
navigation/models.py
navigation/tests.py
zamtools_navigation.egg-info/PKG-INFO
zamtools_navigation.egg-info/SOURCES.txt
zamtools_navigation.egg-info/dependency_links.txt
zamtools_navigation.egg-info/not-zip-safe
zamtools_navigation.egg-info/top_level.txt