Metadata-Version: 1.0
Name: zamtools-navigation
Version: 1.0
Summary: Django application for displaying and tracking site navigation
Home-page: http://code.google.com/p/zamtools-navigation/
Author: Ian Zamojc
Author-email: zamtools@zamtools.com
License: UNKNOWN
Platform: UNKNOWN
Classifier: Development Status :: 4 - Beta
Classifier: Environment :: Web Environment
Classifier: Framework :: Django
Classifier: Intended Audience :: Developers
Classifier: License :: OSI Approved :: BSD License
Classifier: Operating System :: OS Independent
Classifier: Programming Language :: Python
Classifier: Topic :: Utilities
